Workbook

Sheet Assumptions
B2: Uniliver BD-DCF Valuation
B3: Assumptions
B4: Input | C4: Value
B5: Revenue growth rate (Yr 1) | C5: 0.1
B6: Revenue growth rate (Yr 2) | C6: 0.09
B7: Revenue growth rate (Yr 3) | C7: 0.08
B8: Revenue growth rate (Yr 4) | C8: 0.07
B9: Revenue growth rate (Yr 5) | C9: 0.06
B10: EBITDA margin | C10: 0.18
B11: Tax rate | C11: 0.275
B12: D&A (% of revenue) | C12: 0.03
B13: CapEx (% of revenue) | C13: 0.035
B14: Change in NWC (% of revenue) | C14: 0.01
B15: Risk-free rate | C15: 0.11
B16: Equity risk premium | C16: 0.06
... B20: Terminal growth rate | C20: 0.05
B22: Source: placeholder figures replace with Unilever Bangladesh annual report / DSE filing data
B24: Cost of Equity (CAPM) | C24: =C15+C17*C16 -> 0.161
B25: Cost of Debt (after-tax) | C25: =C18*(1-C11) -> 0.06525
B26: WACC | C26: =C24*(1-C19)+C25*C19 -> 0.151425

Sheet DCF
B2: DCF — Revenue Build & Free Cash Flow
B4: ($ mm) | C4: 2025A | D4: 2026E | E4: 2027E | F4: 2028E | G4: 2029E | H4: 2030E
B5: Revenue | C5: 2000 | D5: =C5*(1+Assumptions!C5) -> 2200 | E5: =D5*(1+Assumptions!C6) -> 2398 | F5: =E5*(1+Assumptions!C7) -> 2589.84 | G5: =F5*(1+Assumptions!C8) -> 2771.1288 | H5: =G5*(1+Assumptions!C9) -> 2937.3965
B6: EBITDA | C6: =C5*Assumptions!$C$10 -> 360 | D6: =D5*Assumptions!$C$10 -> 396 | E6: =E5*Assumptions!$C$10 -> 431.64 | F6: =F5*Assumptions!$C$10 -> 466.1712 | G6: =G5*Assumptions!$C$10 -> 498.80318 | H6: =H5*Assumptions!$C$10 -> 528.73138
B7: Less: D&A | C7: =-C5*Assumptions!$C$12 -> -60 | D7: =-D5*Assumptions!$C$12 -> -66 | E7: =-E5*Assumptions!$C$12 -> -71.94 | F7: =-F5*Assumptions!$C$12 -> -77.6952 | G7: =-G5*Assumptions!$C$12 -> -83.133864 | H7: =-H5*Assumptions!$C$12 -> -88.121896
B8: EBIT | C8: =C6+C7 -> 300 | D8: =D6+D7 -> 330 | E8: =E6+E7 -> 359.7 | F8: =F6+F7 -> 388.476 | G8: =G6+G7 -> 415.66932 | H8: =H6+H7 -> 440.60948
B9: Less: Tax on EBIT | C9: =-C8*Assumptions!$C$11 -> -82.5 | D9: =-D8*Assumptions!$C$11 -> -90.75 | E9: =-E8*Assumptions!$C$11 -> -98.9175 | F9: =-F8*Assumptions!$C$11 -> -106.8309 | G9: =-G8*Assumptions!$C$11 -> -114.30906 | H9: =-H8*Assumptions!$C$11 -> -121.16761
B10: NOPAT | C10: =C8+C9 -> 217.5 | D10: =D8+D9 -> 239.25 | E10: =E8+E9 -> 260.7825 | F10: =F8+F9 -> 281.6451 | G10: =G8+G9 -> 301.36026 | H10: =H8+H9 -> 319.44187
B11: Add back: D&A | C11: =-C7 -> 60 | D11: =-D7 -> 66 | E11: =-E7 -> 71.94 | F11: =-F7 -> 77.6952 | G11: =-G7 -> 83.133864 | H11: =-H7 -> 88.121896
B12: Less: CapEx | C12: =-C5*Assumptions!$C$13 -> -70 | D12: =-D5*Assumptions!$C$13 -> -77 | E12: =-E5*Assumptions!$C$13 -> -83.93 | F12: =-F5*Assumptions!$C$13 -> -90.6444 | G12: =-G5*Assumptions!$C$13 -> -96.989508 | H12: =-H5*Assumptions!$C$13 -> -102.80888
B13: Less: Change in NWC | C13: =-C5*Assumptions!$C$14 -> -20 | D13: =-D5*Assumptions!$C$14 -> -22 | E13: =-E5*Assumptions!$C$14 -> -23.98 | F13: =-F5*Assumptions!$C$14 -> -25.8984 | G13: =-G5*Assumptions!$C$14 -> -27.711288 | H13: =-H5*Assumptions!$C$14 -> -29.373965
B14: Unlevered Free Cash Flow | C14: =C10+C11+C12+C13 -> 187.5 | D14: =D10+D11+D12+D13 -> 206.25 | E14: =E10+E11+E12+E13 -> 224.8125 | F14: =F10+F11+F12+F13 -> 242.7975 | G14: =G10+G11+G12+G13 -> 259.79332 | H14: =H10+H11+H12+H13 -> 275.38092
B15: Discount period | D15: 1 | E15: 2 | F15: 3 | G15: 4 | H15: 5
B16: Discount factor | D16: =1/(1+Assumptions!$C$19)^D15 -> 0.90909091 | E16: =1/(1+Assumptions!$C$19)^E15 -> 0.82644628 | F16: =1/(1+Assumptions!$C$19)^F15 -> 0.7513148 | G16: =1/(1+Assumptions!$C$19)^G15 -> 0.68301346 | H16: =1/(1+Assumptions!$C$19)^H15 -> 0.62092132
B17: PV of FCF | D17: =D14*D16 -> 187.5 | E17: =E14*E16 -> 185.79545 | F17: =F14*F16 -> 182.41736 | G17: =G14*G16 -> 177.44234 | H17: =H14*H16 -> 170.98989
B20: Valuation Summary
B21: Sum of PV of FCF (Yr 1-5) | C21: =SUM(D17:H17) -> 904.14503
B22: Terminal Value (Gordon Growth) | C22: =H14*(1+Assumptions!$C$20)/(Assumptions!$C$19-Assumptions!$C$20) -> 5782.9994
B23: PV of Terminal Value | C23: =C22*H16 -> 3590.7876
B24: Enterprise Value | C24: =C21+C23 -> 4494.9327
